taskeduler/__init__.py
taskeduler/__main__.py
taskeduler/taskeduler.py
taskeduler/parser/__init__.py
taskeduler/parser/task_parser.py
taskeduler/scheduler/__init__.py
taskeduler/scheduler/execution_rules_manager.py
taskeduler/scheduler/scheduler.py
taskeduler/task/__init__.py
taskeduler/task/task.py
taskeduler/task/task_manager.py
taskeduler/utils/__init__.py
taskeduler/utils/py_utils.py
taskeduler/utils/time_utils.py
taskeduler-1.0.1.dist-info/METADATA
taskeduler-1.0.1.dist-info/WHEEL
taskeduler-1.0.1.dist-info/entry_points.txt
taskeduler-1.0.1.dist-info/top_level.txt
taskeduler-1.0.1.dist-info/RECORD
