Metadata-Version: 2.1
Name: taskeduler
Version: 1.0.1
Summary: Schedule your tasks, easily
Home-page: https://github.com/alexgcarretero/taskeduler
Author: @alexgcarretero
License: MIT
Platform: UNKNOWN
Classifier: License :: OSI Approved :: MIT License
Classifier: Programming Language :: Python :: 3
Classifier: Programming Language :: Python :: 3.9
Requires-Dist: PyYAML
